transcoder
