Metadata-Version: 1.0
Name: aws-video-transcoder
Version: 0.3
Summary: Transcodes videos to web-proof formats such as webp.
Home-page: https://github.com/zwennesm/aws-video-transcoder
Author: Martijn Zwennes
Author-email: martijn.zwennes@debijenkorf.nl
License: MIT
Platform: UNKNOWN
